NLab/__init__.py
NLab/Base/base_root.cp311-win_amd64.pyd
NLab/Base/servers.cp311-win_amd64.pyd
NLab/DataView/log_browser.cp311-win_amd64.pyd
NLab/DataView/run.py
NLab/Instruments/Instrument.cp311-win_amd64.pyd
NLab/Manual/view.pdf
NLab/Utils/common.cp311-win_amd64.pyd
NLab/Utils/loadcsv.cp311-win_amd64.pyd
NLab/Utils/pltr.cp311-win_amd64.pyd
NLab/Utils/rwdata.cp311-win_amd64.pyd
NLab/Utils/rwjson.cp311-win_amd64.pyd
NLab/Utils/tracer.cp311-win_amd64.pyd
NLab/Utils/multiploter/adj.cp311-win_amd64.pyd
NLab/Utils/multiploter/conf.cp311-win_amd64.pyd
NLab/Utils/multiploter/ds.cp311-win_amd64.pyd
NLab/Utils/multiploter/mulpltr.cp311-win_amd64.pyd
NLab/Utils/multiploter/ploter.cp311-win_amd64.pyd
NLab/Utils/multiploter/que.cp311-win_amd64.pyd
njlab-1.0.0.dist-info/METADATA
njlab-1.0.0.dist-info/WHEEL
njlab-1.0.0.dist-info/top_level.txt
njlab-1.0.0.dist-info/RECORD
