Metadata-Version: 2.1
Name: njlab
Version: 1.0.0
Summary: njlab
Home-page: UNKNOWN
Author: OrkeshNurbolat
Author-email: MG1922077@smail.nju.edu.cn
License: MIT
Platform: UNKNOWN
Classifier: License :: OSI Approved :: MIT License
Classifier: Programming Language :: Python :: 3.12
Classifier: Programming Language :: Python :: 3.11
Classifier: Programming Language :: Python :: 3.10
Classifier: Programming Language :: Python :: 3.9
Classifier: Programming Language :: Python :: 3.8
Classifier: Operating System :: OS Independent
Requires-Python: >=3.8
Provides-Extra: dev
Requires-Dist: pytest >=7.0 ; extra == 'dev'
Requires-Dist: twine >=4.0.2 ; extra == 'dev'
